[{"name": "Rishabh", "password": "1234", "email": "123@hewdj"}, {"name": "sonu", "password": "dsf", "email": "dfs"}, {"name": "Rhythm", "password": "loli", "email": "loli_ldki"}, {"name": "Rhythm", "password": "hello", "email": "heello"}, {"name": "sonu", "password": "dsf", "email": "dfs"}, {"name": "sonu", "password": "dsf", "email": "dfs"}, {"name": "sonu", "password": "dsf", "email": "dfs"}, {"name": "sonu", "password": "dsf", "email": "dfs"}, {"name": "sonu", "password": "dsf", "email": "ist"}]